{
  "sport": "NFL",
  "year": 2025,
  "week": 3,
  "slateType": "SHOWDOWN",
  "slateDate": "2025-09-18",
  "contest": {
    "site": "DraftKings",
    "contestName": "TNF Showdown",
    "siteContestId": "NFL_2025_WK03_TNF_SHOWDOWN_2025-09-18_dolphins_bills",
    "entryFeeCents": null,
    "entries": null,
    "topPrizeCents": 50000000,
    "totalOwnershipBp": 20510
  },
  "winner": {
    "username": "DukeNasty",
    "points": 113.42,
    "maxEntries": 3
  },
  "lineup": {
    "salaryUsed": 49700,
    "totalPoints": 113.42,
    "items": [
      {
        "rosterSpot": "CAPTAIN",
        "name": "D. Kincaid",
        "position": "TE",
        "team": "BUF",
        "salary": 8100,
        "points": 26.4,
        "ownershipPercent": 3.7
      },
      {
        "rosterSpot": "FLEX",
        "name": "J. Allen",
        "position": "QB",
        "team": "BUF",
        "salary": 12400,
        "points": 23.02,
        "ownershipPercent": 82.6
      },
      {
        "rosterSpot": "FLEX",
        "name": "J. Cook III",
        "position": "RB",
        "team": "BUF",
        "salary": 10600,
        "points": 23.8,
        "ownershipPercent": 60.2
      },
      {
        "rosterSpot": "FLEX",
        "name": "T. Hill",
        "position": "WR",
        "team": "MIA",
        "salary": 9800,
        "points": 15.9,
        "ownershipPercent": 32.2
      },
      {
        "rosterSpot": "FLEX",
        "name": "K. Shakir",
        "position": "WR",
        "team": "BUF",
        "salary": 6600,
        "points": 14.5,
        "ownershipPercent": 24.3
      },
      {
        "rosterSpot": "FLEX",
        "name": "O. Gordon II",
        "position": "RB",
        "team": "MIA",
        "salary": 2200,
        "points": 9.8,
        "ownershipPercent": 2.1
      }
    ]
  }
}
